otlp_json/__init__.py
otlp_json/py.typed
otlp_json-1.0.0.dist-info/METADATA
otlp_json-1.0.0.dist-info/WHEEL
otlp_json-1.0.0.dist-info/RECORD
