Metadata-Version: 2.4
Name: otlp-json
Version: 1.0.0
Summary: 🐍Lightweight OTEL span to JSON converter, no dependencies, pure Python🐍
Project-URL: Repository, https://github.com/dimaqq/otlp-json
Project-URL: Issues, https://github.com/dimaqq/otlp-json/issues
License: Apache License (2.0)
Classifier: Development Status :: 3 - Alpha
Classifier: Framework :: OpenTelemetry
Classifier: Framework :: OpenTelemetry :: Exporters
Classifier: Intended Audience :: Developers
Classifier: License :: OSI Approved :: Apache Software License
Classifier: Natural Language :: English
Classifier: Operating System :: OS Independent
Classifier: Programming Language :: Python
Classifier: Programming Language :: Python :: 3
Classifier: Programming Language :: Python :: 3 :: Only
Classifier: Programming Language :: Python :: 3.8
Classifier: Programming Language :: Python :: 3.9
Classifier: Programming Language :: Python :: 3.10
Classifier: Programming Language :: Python :: 3.11
Classifier: Programming Language :: Python :: 3.12
Classifier: Programming Language :: Python :: 3.13
Classifier: Programming Language :: Python :: 3.14
Classifier: Programming Language :: Python :: Implementation :: CPython
Classifier: Programming Language :: Python :: Implementation :: PyPy
Classifier: Topic :: Software Development :: Libraries
Requires-Python: >=3.8
